CaesarCipher/Decryption.py
CaesarCipher/Encryption.py
CaesarCipher/__init__.py
caesarcipher_extended-2.9.1.dist-info/licenses/LICENSE
caesarcipher_extended-2.9.1.dist-info/METADATA
caesarcipher_extended-2.9.1.dist-info/WHEEL
caesarcipher_extended-2.9.1.dist-info/top_level.txt
caesarcipher_extended-2.9.1.dist-info/RECORD
