Metadata-Version: 2.4
Name: CaesarCipher.extended
Version: 2.9.1
Summary: Implementation of the Caesar Cipher encryption algorithm in Python. Unlike the classic, it also shifts numbers, symbols & even emojis! Focused on simplicity and Efficiency.
Author-email: ViratiAkiraNandhanReddy <contact.viratiakiranandhanreddy+python@gmail.com>
License:                     GNU GENERAL PUBLIC LICENSE
Project-URL: Homepage, https://viratiakiranandhanreddy.github.io/CaesarCipher.extended/
Project-URL: Repository, https://github.com/ViratiAkiraNandhanReddy/CaesarCipher.extended
Project-URL: Issues, https://github.com/ViratiAkiraNandhanReddy/CaesarCipher.extended/issues
Keywords: Caesar Cipher,encryption,decryption,cryptography,Python,ViratiAkiraNandhanReddy,VIRATI AKIRANANDHAN REDDY
Classifier: Programming Language :: Python :: 3
Classifier: License :: OSI Approved :: GNU General Public License v3 (GPLv3)
Classifier: Operating System :: OS Independent
Classifier: Development Status :: 5 - Production/Stable
Classifier: Intended Audience :: Developers
Classifier: Topic :: Security :: Cryptography
Classifier: Topic :: Software Development :: Libraries :: Python Modules
Requires-Python: >=3.11
License-File: LICENSE
Dynamic: license-file
